crawlinsta/__init__.py
crawlinsta/collecting/__init__.py
crawlinsta/collecting/base.py
crawlinsta/collecting/comments_of_post.py
crawlinsta/collecting/followers_of_user.py
crawlinsta/collecting/following_hashtags_of_user.py
crawlinsta/collecting/followings_of_user.py
crawlinsta/collecting/friendship_status.py
crawlinsta/collecting/keyword_search.py
crawlinsta/collecting/likers_of_post.py
crawlinsta/collecting/media.py
crawlinsta/collecting/posts_by_music_id.py
crawlinsta/collecting/posts_of_user.py
crawlinsta/collecting/reels_of_user.py
crawlinsta/collecting/tagged_posts_of_user.py
crawlinsta/collecting/top_posts_of_hashtag.py
crawlinsta/collecting/user_info.py
crawlinsta/constants.py
crawlinsta/data_extraction.py
crawlinsta/decorators.py
crawlinsta/login.py
crawlinsta/schemas.py
crawlinsta/utils.py
crawlinsta/webdriver.py
crawlinsta-0.1.0.dist-info/LICENSE
crawlinsta-0.1.0.dist-info/METADATA
crawlinsta-0.1.0.dist-info/WHEEL
crawlinsta-0.1.0.dist-info/RECORD
