Metadata-Version: 2.1
Name: crawlinsta
Version: 0.1.0
Summary: A python package for crawling instagram based on selenium.
Home-page: https://github.com/zhiwei2017/crawlinsta
License: MIT
Author: Zhiwei Zhang
Author-email: zhiwei2017@gmail.com
Requires-Python: >=3.10,<4.0
Classifier: License :: OSI Approved :: MIT License
Classifier: Programming Language :: Python :: 3
Classifier: Programming Language :: Python :: 3.10
Classifier: Programming Language :: Python :: 3.11
Classifier: Programming Language :: Python :: 3.12
Requires-Dist: blinker (>=1.7,<1.8)
Requires-Dist: joblib (>=1.3,<1.4)
Requires-Dist: pydantic (>=2.4,<2.5)
Requires-Dist: selenium (>=4.12,<4.13)
Requires-Dist: selenium-wire (>=5.1,<5.2)
Project-URL: Repository, https://github.com/zhiwei2017/crawlinsta
